time_limitation_module/__init__.py
time_limitation_module/start_limitation.py
time_limitation_module-2.0.2.dist-info/METADATA
time_limitation_module-2.0.2.dist-info/WHEEL
time_limitation_module-2.0.2.dist-info/top_level.txt
time_limitation_module-2.0.2.dist-info/RECORD
