Metadata-Version: 2.1
Name: time-limitation-module
Version: 2.0.2
Summary: time limitation module
Home-page: UNKNOWN
Author: leooyang
Author-email: leooyang@futunn.com
License: UNKNOWN
Platform: UNKNOWN
Requires-Python: ==3.7.5
Requires-Dist: pydantic ==1.10.7
Requires-Dist: django ==3.2.15
Requires-Dist: pyrpc ==0.6.3
Requires-Dist: cmlb ==0.1.0
Requires-Dist: cmlb-api-client ==0.3.1
Requires-Dist: protobuf ==3.17.3
Requires-Dist: srpc-pb2 ==0.6.6
Requires-Dist: python ==3.7.5
